[
{"type_name":"黑鬼淫妻","type_id":"/list/base-remen3-hgyq-1.js"},
{"type_name":"黑丝玉足","type_id":"/list/base-remen2-hsyz-1.js"},
{"type_name":"欧美大片","type_id":"/list/base-vip-omdp-1.js"},
{"type_name":"国产精品","type_id":"/list/base-shipin-gcjp-1.js"},
{"type_name":"欧美精品","type_id":"/list/base-shipin-omjp-1.js"},
{"type_name":"吃瓜黑料","type_id":"/list/base-remen2-cghl-1.js"},
{"type_name":"女优-112","type_id":"/shipin/nvyou-112-1.js"},
{"type_name":"新片速递","type_id":"/list/base-remen-xpsd-1.js"},
{"type_name":"独家精选","type_id":"/list/base-remen-djjx-1.js"},
{"type_name":"国产传媒","type_id":"/list/base-remen-gccm-1.js"},
{"type_name":"精品高清","type_id":"/list/base-remen-jpgq-1.js"},
{"type_name":"著名厂商","type_id":"/list/base-remen-zmcs-1.js"},
{"type_name":"探花大神","type_id":"/list/base-remen-thss-1.js"},
{"type_name":"私拍泄密","type_id":"/list/base-remen-spxm-1.js"},
{"type_name":"AV解说","type_id":"/list/base-remen-avjs-1.js"},
{"type_name":"反差少女","type_id":"/list/base-remen2-fcsn-1.js"},
{"type_name":"绳艺调教","type_id":"/list/base-remen2-sytj-1.js"},
{"type_name":"觅圈正妹","type_id":"/list/base-remen2-nqzm-1.js"},
{"type_name":"裸播大秀","type_id":"/list/base-remen2-lbdx-1.js"},
{"type_name":"主播艳舞","type_id":"/list/base-remen2-zbyw-1.js"},
{"type_name":"私人订制","type_id":"/list/base-remen2-srdz-1.js"},
{"type_name":"VR色情","type_id":"/list/base-remen3-vrsq-1.js"},
{"type_name":"巨乳嫩穴","type_id":"/list/base-remen3-jlnx-1.js"},
{"type_name":"男同拉拉","type_id":"/list/base-remen3-ntll-1.js"},
{"type_name":"御宅伪娘","type_id":"/list/base-remen3-yzwn-1.js"},
{"type_name":"泄密外流","type_id":"/list/base-remen3-xmwl-1.js"},
{"type_name":"知名网黄","type_id":"/list/base-remen3-zmwh-1.js"},
{"type_name":"禁漫里番","type_id":"/list/base-remen3-jmlf-1.js"},
{"type_name":"猫咪推荐","type_id":"/list/base-vip-mmtj-1.js"},
{"type_name":"原创国产","type_id":"/list/base-vip-ycgc-1.js"},
{"type_name":"制服淫穴","type_id":"/list/base-vip-zfyx-1.js"},
{"type_name":"换脸AI区","type_id":"/list/base-vip-hlaiq-1.js"},
{"type_name":"三级综艺","type_id":"/list/base-vip-sjzy-1.js"},
{"type_name":"次元动漫","type_id":"/list/base-vip-cydm-1.js"},
{"type_name":"同性恋区","type_id":"/list/base-vip-txzq-1.js"},
{"type_name":"短视频","type_id":"/list/base-shipin-dsp-1.js"},
{"type_name":"美女主播","type_id":"/list/base-shipin-mnzb-1.js"},
{"type_name":"中文字幕","type_id":"/list/base-shipin-zwzm-1.js"},
{"type_name":"亚洲无码","type_id":"/list/base-shipin-yzwm-1.js"},
{"type_name":"精彩动漫","type_id":"/list/base-shipin-crdm-1.js"},
{"type_name":"女优-156","type_id":"/shipin/nvyou-156-1.js"},
{"type_name":"女优-25993","type_id":"/shipin/nvyou-25993-1.js"},
{"type_name":"女优-20912","type_id":"/shipin/nvyou-20912-1.js"},
{"type_name":"女优-171","type_id":"/shipin/nvyou-171-1.js"},
{"type_name":"女优-20320","type_id":"/shipin/nvyou-20320-1.js"},
{"type_name":"女优-20637","type_id":"/shipin/nvyou-20637-1.js"},
{"type_name":"女优-24233","type_id":"/shipin/nvyou-24233-1.js"},
{"type_name":"女优-22863","type_id":"/shipin/nvyou-22863-1.js"},
{"type_name":"女优-25505","type_id":"/shipin/nvyou-25505-1.js"},
{"type_name":"女优-25196","type_id":"/shipin/nvyou-25196-1.js"},
{"type_name":"女优-25409","type_id":"/shipin/nvyou-25409-1.js"},
{"type_name":"女优-25294","type_id":"/shipin/nvyou-25294-1.js"},
{"type_name":"女优-24074","type_id":"/shipin/nvyou-24074-1.js"},
{"type_name":"女优-23878","type_id":"/shipin/nvyou-23878-1.js"},
{"type_name":"女优-238","type_id":"/shipin/nvyou-238-1.js"},
{"type_name":"女优-23373","type_id":"/shipin/nvyou-23373-1.js"},
{"type_name":"女优-23116","type_id":"/shipin/nvyou-23116-1.js"},
{"type_name":"女优-22657","type_id":"/shipin/nvyou-22657-1.js"},
{"type_name":"女优-22386","type_id":"/shipin/nvyou-22386-1.js"},
{"type_name":"女优-155","type_id":"/shipin/nvyou-155-1.js"},
{"type_name":"女优-207","type_id":"/shipin/nvyou-207-1.js"},
{"type_name":"女优-212","type_id":"/shipin/nvyou-212-1.js"},
{"type_name":"女优-210","type_id":"/shipin/nvyou-210-1.js"},
{"type_name":"女优-215","type_id":"/shipin/nvyou-215-1.js"},
{"type_name":"女优-218","type_id":"/shipin/nvyou-218-1.js"},
{"type_name":"女优-216","type_id":"/shipin/nvyou-216-1.js"},
{"type_name":"女优-221","type_id":"/shipin/nvyou-221-1.js"},
{"type_name":"女优-217","type_id":"/shipin/nvyou-217-1.js"},
{"type_name":"女优-108","type_id":"/shipin/nvyou-108-1.js"},
{"type_name":"女优-22030","type_id":"/shipin/nvyou-22030-1.js"},
{"type_name":"女优-21826","type_id":"/shipin/nvyou-21826-1.js"},
{"type_name":"女优-21793","type_id":"/shipin/nvyou-21793-1.js"},
{"type_name":"女优-21762","type_id":"/shipin/nvyou-21762-1.js"},
{"type_name":"女优-88","type_id":"/shipin/nvyou-88-1.js"},
{"type_name":"女优-21679","type_id":"/shipin/nvyou-21679-1.js"},
{"type_name":"女优-21582","type_id":"/shipin/nvyou-21582-1.js"},
{"type_name":"女优-110","type_id":"/shipin/nvyou-110-1.js"},
{"type_name":"女优-20607","type_id":"/shipin/nvyou-20607-1.js"},
{"type_name":"女优-20462","type_id":"/shipin/nvyou-20462-1.js"},
{"type_name":"女优-19804","type_id":"/shipin/nvyou-19804-1.js"},
{"type_name":"女优-109","type_id":"/shipin/nvyou-109-1.js"},
{"type_name":"女优-213","type_id":"/shipin/nvyou-213-1.js"},
{"type_name":"女优-161","type_id":"/shipin/nvyou-161-1.js"},
{"type_name":"女优-116","type_id":"/shipin/nvyou-116-1.js"},
{"type_name":"女优-173","type_id":"/shipin/nvyou-173-1.js"},
{"type_name":"女优-214","type_id":"/shipin/nvyou-214-1.js"},
{"type_name":"女优-166","type_id":"/shipin/nvyou-166-1.js"},
{"type_name":"女优-126","type_id":"/shipin/nvyou-126-1.js"},
{"type_name":"女优-229","type_id":"/shipin/nvyou-229-1.js"},
{"type_name":"女优-236","type_id":"/shipin/nvyou-236-1.js"},
{"type_name":"女优-225","type_id":"/shipin/nvyou-225-1.js"},
{"type_name":"女优-234","type_id":"/shipin/nvyou-234-1.js"},
{"type_name":"女优-233","type_id":"/shipin/nvyou-233-1.js"},
{"type_name":"女优-228","type_id":"/shipin/nvyou-228-1.js"},
{"type_name":"女优-226","type_id":"/shipin/nvyou-226-1.js"}
]